maths_mcp/__init__.py
maths_mcp/main.py
maths_mcp/utils.py
maths_mcp-0.1.10.dist-info/licenses/LICENSE
maths_mcp-0.1.10.dist-info/METADATA
maths_mcp-0.1.10.dist-info/WHEEL
maths_mcp-0.1.10.dist-info/entry_points.txt
maths_mcp-0.1.10.dist-info/top_level.txt
maths_mcp-0.1.10.dist-info/RECORD
