Metadata-Version: 2.4
Name: maths-mcp
Version: 0.1.10
Summary: Does all the cool maths related stuff for your LLM. Goal is to support all the maths tools we can support.
Requires-Python: >=3.10
License-File: LICENSE
Requires-Dist: mcp[cli]>=1.6.0
Dynamic: license-file
